setup.py
bin/prebuild.py
prebuild/__init__.py
prebuild.me.egg-info/PKG-INFO
prebuild.me.egg-info/SOURCES.txt
prebuild.me.egg-info/dependency_links.txt
prebuild.me.egg-info/top_level.txt