Metadata-Version: 1.0
Name: prebuild.me
Version: 0.0.1
Summary: Python CLI for prebuild.me
Home-page: UNKNOWN
Author: Brian Lauber
Author-email: constructible.truth@gmail.com
License: MIT
Platform: UNKNOWN
